mapactionpy_controller/__init__.py
mapactionpy_controller/check_naming_convention.py
mapactionpy_controller/config_verify.py
mapactionpy_controller/crash_move_folder.py
mapactionpy_controller/data_search.py
mapactionpy_controller/data_source.py
mapactionpy_controller/event.py
mapactionpy_controller/label_class.py
mapactionpy_controller/layer_properties.py
mapactionpy_controller/map_cookbook.py
mapactionpy_controller/map_doc.py
mapactionpy_controller/map_layer.py
mapactionpy_controller/map_recipe.py
mapactionpy_controller/map_report.py
mapactionpy_controller/map_result.py
mapactionpy_controller/name_clause_validators.py
mapactionpy_controller/name_convention.py
mapactionpy_controller/product_bundle_definition.py
mapactionpy_controller/tests/__init__.py
mapactionpy_controller/tests/fixtures.py
mapactionpy_controller/tests/test_check_naming_convention.py
mapactionpy_controller/tests/test_config_verify.py
mapactionpy_controller/tests/test_data_search.py
mapactionpy_controller/tests/test_event.py
mapactionpy_controller/tests/test_layer_properties.py
mapactionpy_controller/tests/test_mapactionpy_controller.py
mapactionpy_controller/tests/test_name_convention.py
mapactionpy_controller/tests/test_to_integrate_from_arcmap.py
mapactionpy_controller-0.10.1.dist-info/METADATA
mapactionpy_controller-0.10.1.dist-info/WHEEL
mapactionpy_controller-0.10.1.dist-info/top_level.txt
mapactionpy_controller-0.10.1.dist-info/RECORD
