Metadata-Version: 2.1
Name: mapactionpy-controller
Version: 0.10.1
Summary: Controls the workflow of map and infographic production
Home-page: http://github.com/mapaction/mapactionpy_controller
Author: MapAction
Author-email: github@mapaction.com
License: GPL3
Platform: UNKNOWN
Classifier: Development Status :: 2 - Pre-Alpha
Classifier: Programming Language :: Python :: 2.7
Classifier: Programming Language :: Python :: 3
Classifier: License :: OSI Approved :: GNU General Public License v3 (GPLv3)
Classifier: Operating System :: OS Independent
Requires-Dist: jsonpickle
Requires-Dist: six
